musicnotes/__init__.py
musicnotes/musicnotes.py
musicnotes/sound.py
musicnotes/assets/guitar/highA#guitar.mp3
musicnotes/assets/guitar/highAguitar.mp3
musicnotes/assets/guitar/highBguitar.mp3
musicnotes/assets/guitar/highC#guitar.mp3
musicnotes/assets/guitar/highCguitar.mp3
musicnotes/assets/guitar/highD#guitar.mp3
musicnotes/assets/guitar/highDguitar.mp3
musicnotes/assets/guitar/highEguitar.mp3
musicnotes/assets/guitar/highF#guitar.mp3
musicnotes/assets/guitar/highFguitar.mp3
musicnotes/assets/guitar/highG#guitar.mp3
musicnotes/assets/guitar/highGguitar.mp3
musicnotes/assets/guitar/lowA#guitar.mp3
musicnotes/assets/guitar/lowAguitar.mp3
musicnotes/assets/guitar/lowBguitar.mp3
musicnotes/assets/guitar/lowC#guitar.mp3
musicnotes/assets/guitar/lowCguitar.mp3
musicnotes/assets/guitar/lowD#guitar.mp3
musicnotes/assets/guitar/lowDguitar.mp3
musicnotes/assets/guitar/lowEguitar.mp3
musicnotes/assets/guitar/lowF#guitar.mp3
musicnotes/assets/guitar/lowFguitar.mp3
musicnotes/assets/guitar/lowG#guitar.mp3
musicnotes/assets/guitar/lowGguitar.mp3
musicnotes/assets/guitar/midA#guitar.mp3
musicnotes/assets/guitar/midAguitar.mp3
musicnotes/assets/guitar/midBguitar.mp3
musicnotes/assets/guitar/midC#guitar.mp3
musicnotes/assets/guitar/midCguitar.mp3
musicnotes/assets/guitar/midD#guitar.mp3
musicnotes/assets/guitar/midDguitar.mp3
musicnotes/assets/guitar/midEguitar.mp3
musicnotes/assets/guitar/midF#guitar.mp3
musicnotes/assets/guitar/midFguitar.mp3
musicnotes/assets/guitar/midG#guitar.mp3
musicnotes/assets/guitar/midGguitar.mp3
musicnotes/assets/piano/highA#piano.mp3
musicnotes/assets/piano/highApiano.mp3
musicnotes/assets/piano/highBpiano.mp3
musicnotes/assets/piano/highC#piano.mp3
musicnotes/assets/piano/highCpiano.mp3
musicnotes/assets/piano/highD#piano.mp3
musicnotes/assets/piano/highDpiano.mp3
musicnotes/assets/piano/highEpiano.mp3
musicnotes/assets/piano/highF#piano.mp3
musicnotes/assets/piano/highFpiano.mp3
musicnotes/assets/piano/highG#piano.mp3
musicnotes-1.14.dist-info/licenses/LICENSE
musicnotes-1.14.dist-info/METADATA
musicnotes-1.14.dist-info/WHEEL
musicnotes-1.14.dist-info/top_level.txt
musicnotes-1.14.dist-info/RECORD
