Metadata-Version: 2.4
Name: musicnotes
Version: 1.14
Summary: Play music notes in your Python scripts with ease.
Author-email: Mustaeen Ahmed <contact@mustaeen.dev>
License-Expression: MIT
Keywords: sound,music,mp3,wave,wav,media,song,play,audio,notes,music notes,melody
Classifier: Intended Audience :: Developers
Classifier: Operating System :: OS Independent
Classifier: Programming Language :: Python :: 3
Classifier: Topic :: Multimedia :: Sound/Audio :: MIDI
Classifier: Topic :: Multimedia :: Sound/Audio :: Players
Requires-Python: >=3.6
License-File: LICENSE
Dynamic: license-file
